{
    "fluentMethods": true,
    "relationships": [],
    "fields": [
        {
            "fieldName": "deviceProducer",
            "fieldType": "String"
        },
        {
            "fieldName": "deviceModel",
            "fieldType": "String",
            "fieldValidateRules": [
                "required"
            ]
        },
        {
            "fieldName": "sensorType",
            "fieldType": "String",
            "fieldValidateRules": [
                "required"
            ]
        }
    ],
    "changelogDate": "20170509093559",
    "entityTableName": "device_type",
    "dto": "no",
    "pagination": "no",
    "service": "no"
}